python_firebase_url_shortener/__init__.py
python_firebase_url_shortener/test_url_shortener.py
python_firebase_url_shortener/url_shortener.py
python_firebase_url_shortener-1.0.0.dist-info/LICENSE
python_firebase_url_shortener-1.0.0.dist-info/METADATA
python_firebase_url_shortener-1.0.0.dist-info/WHEEL
python_firebase_url_shortener-1.0.0.dist-info/top_level.txt
python_firebase_url_shortener-1.0.0.dist-info/RECORD
