Metadata-Version: 2.1
Name: python-firebase-url-shortener
Version: 1.0.0
Summary: A Python Client for Firebase Dynamic Links to Shorten URLs.
Home-page: https://github.com/saadmk11/firebase_url_shortener
Author: saadmk11
Author-email: saad.mk112@gmail.com
License: GNU Public License
Platform: UNKNOWN
Classifier: Programming Language :: Python :: 3
Classifier: Programming Language :: Python :: 3.6
Classifier: Programming Language :: Python :: 3.7
Classifier: License :: OSI Approved :: GNU General Public License v3 (GPLv3)
Classifier: Operating System :: OS Independent
Requires-Dist: requests (==2.21.0)
